xserver/__init__.py
xserver/attribute.py
xserver/http/__init__.py
xserver/http/proxy.py
xserver/sock/__init__.py
xserver/sock/header.py
xserver/sock/proxy.py
xserver/unittest/http/__init__.py
xserver/unittest/http/test_proxy.py
xserver/unittest/sock/__init__.py
xserver/unittest/sock/test_header.py
xserver/unittest/sock/test_proxy.py
xser-0.5.1.dist-info/LICENSE
xser-0.5.1.dist-info/METADATA
xser-0.5.1.dist-info/WHEEL
xser-0.5.1.dist-info/top_level.txt
xser-0.5.1.dist-info/zip-safe
xser-0.5.1.dist-info/RECORD
