Metadata-Version: 2.1
Name: xser
Version: 0.5.1
Summary: Socket and HTTP Server
Home-page: https://github.com/bondbox/xser/
Author: Mingzhe Zou
Author-email: zoumingzhe@outlook.com
License: GPLv2
Project-URL: Source Code, https://github.com/bondbox/xser/
Project-URL: Bug Tracker, https://github.com/bondbox/xser/issues
Project-URL: Documentation, https://github.com/bondbox/xser/
Keywords: command-line,argparse,argcomplete
Platform: any
Classifier: Programming Language :: Python
Classifier: Programming Language :: Python :: 3
Requires-Python: >=3.8
License-File: LICENSE
Requires-Dist: xkits-thread >=0.2
Requires-Dist: xhtm >=0.12.1
Requires-Dist: requests
